modules/imem.sv
module imem(
    input wire [31:0] addr,
    output wire [31:0] instruction_out
);

parameter MEM_SIZE_WORDS = 256;
reg [31:0] mem [0:MEM_SIZE_WORDS-1];

initial begin
    $readmemh("assembly/instruction.mem", mem);
end

assign instruction_out = mem[addr[31:2]];

endmodule

modules/pc_plus_4.sv
module pc_plus_4 (
    input wire [31:0] current_pc,
    output wire [31:0] pc_plus_4_value
);

assign pc_plus_4_value = current_pc + 32'd4; 

endmodule;

modules/pc.sv
module pc (
    input wire clk ,
    input wire reset,
    input wire [31:0] next_pc_in,
    output reg [31:0] pc_out
);

always @(posedge clk or posedge reset ) begin
    if(reset) begin
        pc_out <= 32'h00000000;
    end else begin 
        pc_out <= next_pc_in;
    end
end

endmodule

modules/cpu.sv
module cpu(
    input wire clk,
    input wire reset
);

wire [31:0] pc_current_addr;
wire [31:0] pc_plus_4_val;
wire [31:0] fetched_instruction;

pc u_pc (
    .clk (clk),
    .reset (reset),
    .next_pc_in (pc_plus_4_val),
    .pc_out (pc_current_addr)
);

pc_plus_4 u_pc_plus_4 (
    .current_pc (pc_current_addr),
    .pc_plus_4_value (pc_plus_4_val)
);

imem u_imem (
    .addr (pc_current_addr),
    .instruction_out (fetched_instruction)
);

always @(posedge clk) begin
    if (!reset) begin
        $display("PC: 0x%h, Instruction: 0x%h", pc_current_addr, fetched_instruction );
    end
end

endmodule

testbench/cpu_tb.sv
`timescale 1ns/1ps

module cpu_tb;

reg clk;
reg reset;

cpu u_cpu(
    .clk (clk),
    .reset (reset)
);

initial begin
    clk = 0;
    forever #5 clk = ~clk;
end

initial begin
    $dumpfile("cpu_test.vcd");
    $dumpvars(0, cpu_tb);

    reset = 1;
    #20;
    reset = 0;

    #100;

    $display("CPU Fetch Simulation Finished.");
    $finish;

end

endmodule

cpu_test.vcd
$date
	Mon Jul 21 23:56:30 2025
$end
$version
	Icarus Verilog
$end
$timescale
	1ps
$end
$scope module cpu_tb $end
$var reg 1 ! clk $end
$var reg 1 " reset $end
$scope module u_cpu $end
$var wire 1 ! clk $end
$var wire 1 " reset $end
$var wire 32 # pc_plus_4_val [31:0] $end
$var wire 32 $ pc_current_addr [31:0] $end
$var wire 32 % fetched_instruction [31:0] $end
$scope module u_imem $end
$var wire 32 & instruction_out [31:0] $end
$var wire 32 ' addr [31:0] $end
$var parameter 32 ( MEM_SIZE_WORDS $end
$upscope $end
$scope module u_pc $end
$var wire 1 ! clk $end
$var wire 1 " reset $end
$var wire 32 ) next_pc_in [31:0] $end
$var reg 32 * pc_out [31:0] $end
$upscope $end
$scope module u_pc_plus_4 $end
$var wire 32 + current_pc [31:0] $end
$var wire 32 , pc_plus_4_value [31:0] $end
$upscope $end
$upscope $end
$upscope $end
$enddefinitions $end
$comment Show the parameter values. $end
$dumpall
b100000000 (
$end
#0
$dumpvars
b100 ,
b0 +
b0 *
b100 )
b0 '
b10100000000000010010011 &
b10100000000000010010011 %
b0 $
b100 #
1"
0!
$end
#5000
1!
#10000
0!
#15000
1!
#20000
0!
0"
#25000
b101000000000000100010011 %
b101000000000000100010011 &
b1000 #
b1000 )
b1000 ,
b100 $
b100 '
b100 *
b100 +
1!
#30000
0!
#35000
b1000001000000110110011 %
b1000001000000110110011 &
b1100 #
b1100 )
b1100 ,
b1000 $
b1000 '
b1000 *
b1000 +
1!
#40000
0!
#45000
b11111111010111111111000001101111 %
b11111111010111111111000001101111 &
b10000 #
b10000 )
b10000 ,
b1100 $
b1100 '
b1100 *
b1100 +
1!
#50000
0!
#55000
bx %
bx &
b10100 #
b10100 )
b10100 ,
b10000 $
b10000 '
b10000 *
b10000 +
1!
#60000
0!
#65000
b11000 #
b11000 )
b11000 ,
b10100 $
b10100 '
b10100 *
b10100 +
1!
#70000
0!
#75000
b11100 #
b11100 )
b11100 ,
b11000 $
b11000 '
b11000 *
b11000 +
1!
#80000
0!
#85000
b100000 #
b100000 )
b100000 ,
b11100 $
b11100 '
b11100 *
b11100 +
1!
#90000
0!
#95000
b100100 #
b100100 )
b100100 ,
b100000 $
b100000 '
b100000 *
b100000 +
1!
#100000
0!
#105000
b101000 #
b101000 )
b101000 ,
b100100 $
b100100 '
b100100 *
b100100 +
1!
#110000
0!
#115000
b101100 #
b101100 )
b101100 ,
b101000 $
b101000 '
b101000 *
b101000 +
1!
