modules/regfile.sv
module regfile(
    input wire clk,
    input wire reg_write_enable,
    input wire[4:0] read_addr1,
    input wire[4:0] read_addr2,
    input wire[4:0] write_addr,
    input wire[31:0] write_data,
    output wire[31:0] read_data1,
    output wire[31:0] read_data2
);

reg [31:0] registers [0:31];

integer i;

initial begin
    for (int i = 0; i < 32; i = i + 1)begin
        registers[i] = 32'h00000000;
    end
end

always @(posedge clk)begin
    if (reg_write_enable)begin
        if(write_addr != 5'b00000) begin
            registers[write_addr] <= write_data;
        end
    end
end

assign read_data1 = (read_addr1 == 5'b00000) ? 32'h00000000 : registers[read_addr1];

assign read_data2 = (read_addr2 == 5'b00000) ? 32'h00000000 : registers[read_addr2];

endmodule

testbench/regfile_tb.sv
`timescale 1ns/1ps

module regfile_tb;

reg clk;
reg reg_write_enable;
reg [4:0] read_addr1;
reg [4:0] read_addr2;
reg [4:0] write_addr;
reg [31:0] write_data;
wire [31:0] read_data1;
wire [31:0] read_data2;

regfile u_regfile(
    .clk (clk),
    .reg_write_enable (reg_write_enable),
    .read_addr1 (read_addr1),
    .read_addr2 (read_addr2),
    .write_addr (write_addr),
    .read_data1 (read_data1),
    .read_data2 (read_data2),
    .write_data (write_data)
);

initial begin
    clk = 0;
    forever #5 clk = ~clk;
end

initial begin
    reg_write_enable = 0;
    read_addr1 = 0;
    read_addr2 = 0;
    write_addr = 0;
    write_data = 0;

    #10;


    $display("-- Test 1: Write to x1; Read x1 and x0 --");
    reg_write_enable = 1;
    write_addr = 5'd1;
    write_data = 32'hDEADBEEF;
    read_addr1 = 5'd1;
    read_addr2 = 5'd0;

    #10;
    reg_write_enable = 0;
    $display("x1 should be 0xDEADBEEF, x0 should be 0x00000000");
    $display("Read Data 2 (x1): 0x%h, Read Data 2 (x0): 0x%h", read_data1,read_data2);
    
    #10;
    $display("-- Test 2 :Attempt write to x0, Read x0 and x1 --");
    reg_write_enable = 1;
    write_addr = 5'd0;
    write_data = 32'hCAFECAFE;
    read_addr1 = 5'd0;
    read_addr2 = 5'd1;

    #10;
    reg_write_enable = 0;
    $display("x0 should still be 0x00000000, x1 should be 0xDEADBEEF");
    $display("Read Data 1 (x0): 0x%h, Read Data 2 (x1): 0x%h", read_data1, read_data2);

    #10;

    $display("-- Test 3: Write to x5, Read X1 and x5 --");
    reg_write_enable = 1;
    write_addr = 5'd5;
    write_data = 32'h12345678;
    read_addr1 = 5'd1;
    read_addr2 = 5'd5;
    #10;
    reg_write_enable = 0;
    $display("x! should be 0xDEADBEEF, x5 should be 0x12345678");
    $display("Read Data 1 (x1): 0x%h, Read Data 2 (x5): 0x%h", read_data1, read_data2);

    #20;
    $display("Register File Simulation Finished.");
    $finish;
end

    initial begin
        $dumpfile("regfile_test.vcd");
        $dumpvars(0, regfile_tb);
    end

endmodule

regfile_test.vcd
$date
	Wed Aug 13 00:20:11 2025
$end
$version
	Icarus Verilog
$end
$timescale
	1ps
$end
$scope module regfile_tb $end
$var wire 32 ! read_data2 [31:0] $end
$var wire 32 " read_data1 [31:0] $end
$var reg 1 # clk $end
$var reg 5 $ read_addr1 [4:0] $end
$var reg 5 % read_addr2 [4:0] $end
$var reg 1 & reg_write_enable $end
$var reg 5 ' write_addr [4:0] $end
$var reg 32 ( write_data [31:0] $end
$scope module u_regfile $end
$var wire 1 # clk $end
$var wire 5 ) read_addr1 [4:0] $end
$var wire 5 * read_addr2 [4:0] $end
$var wire 1 & reg_write_enable $end
$var wire 5 + write_addr [4:0] $end
$var wire 32 , write_data [31:0] $end
$var wire 32 - read_data2 [31:0] $end
$var wire 32 . read_data1 [31:0] $end
$scope begin $ivl_for_loop0 $end
$var integer 32 / i [31:0] $end
$upscope $end
$upscope $end
$upscope $end
$enddefinitions $end
$comment Show the parameter values. $end
$dumpall
$end
#0
$dumpvars
b100000 /
b0 .
b0 -
b0 ,
b0 +
b0 *
b0 )
b0 (
b0 '
0&
b0 %
b0 $
0#
b0 "
b0 !
$end
#5000
1#
#10000
0#
b1 $
b1 )
b11011110101011011011111011101111 (
b11011110101011011011111011101111 ,
b1 '
b1 +
1&
#15000
b11011110101011011011111011101111 "
b11011110101011011011111011101111 .
1#
#20000
0#
0&
#25000
1#
#30000
b11011110101011011011111011101111 !
b11011110101011011011111011101111 -
b0 "
b0 .
0#
b1 %
b1 *
b0 $
b0 )
b11001010111111101100101011111110 (
b11001010111111101100101011111110 ,
b0 '
b0 +
1&
#35000
1#
#40000
0#
0&
#45000
1#
#50000
b0 !
b0 -
b11011110101011011011111011101111 "
b11011110101011011011111011101111 .
0#
b101 %
b101 *
b1 $
b1 )
b10010001101000101011001111000 (
b10010001101000101011001111000 ,
b101 '
b101 +
1&
#55000
b10010001101000101011001111000 !
b10010001101000101011001111000 -
1#
#60000
0#
0&
